README.rst
setup.py
DSKM/__init__.py
DSKM/_version.py
DSKM/config.py
DSKM/key.py
DSKM/logger.py
DSKM/misc.py
DSKM/operate.py
DSKM/registrar.py
DSKM/utils.py
DSKM/zone.py
DSKM.egg-info/PKG-INFO
DSKM.egg-info/SOURCES.txt
DSKM.egg-info/dependency_links.txt
DSKM.egg-info/entry_points.txt
DSKM.egg-info/requires.txt
DSKM.egg-info/top_level.txt
DSKM/REG/__init__.py
DSKM/REG/joker.py
DSKM/REG/ripe.py