Metadata-Version: 2.1
Name: DSKM
Version: 0.9.0
Summary: DNSsec key management
Home-page: https://github.com/mc3/DSKM
Author: Axel Rau
Author-email: axel.rau@chaos1.de
License: GPLv3
Platform: UNKNOWN
Classifier: Development Status :: 4 - Beta
Classifier: Environment :: Console
Classifier: Intended Audience :: System Administrators
Classifier: License :: OSI Approved :: GNU General Public License (GPL)
Classifier: Operating System :: POSIX
Classifier: Topic :: Internet
Classifier: Topic :: Security :: Cryptography
Classifier: Programming Language :: Python :: 3
Classifier: Programming Language :: Python :: 3 :: Only
Classifier: Programming Language :: Python :: 3.6
Classifier: Programming Language :: Python :: 3.7
Classifier: Natural Language :: English
